[

{"title": "Daf 1",
"key": "Talmud/Yerushalmi/Seder Nezikin/Jerusalem Talmud Avodah Zarah/Daf 1",
"id": "Talmud.Yerushalmi.Seder_Nezikin.Jerusalem_Talmud_Avodah_Zarah.1",
"children": [

{"title": "Halakhah 1",
"key": "Talmud/Yerushalmi/Seder Nezikin/Jerusalem Talmud Avodah Zarah/Daf 1/Halakhah 1",
"id": "Talmud.Yerushalmi.Seder_Nezikin.Jerusalem_Talmud_Avodah_Zarah.1.1",
"children": []},

{"title": "Halakhah 2",
"key": "Talmud/Yerushalmi/Seder Nezikin/Jerusalem Talmud Avodah Zarah/Daf 1/Halakhah 2",
"id": "Talmud.Yerushalmi.Seder_Nezikin.Jerusalem_Talmud_Avodah_Zarah.1.2",
"children": []}]},

{"title": "Daf 2",
"key": "Talmud/Yerushalmi/Seder Nezikin/Jerusalem Talmud Avodah Zarah/Daf 2",
"id": "Talmud.Yerushalmi.Seder_Nezikin.Jerusalem_Talmud_Avodah_Zarah.2",
"children": [

{"title": "Halakhah 1",
"key": "Talmud/Yerushalmi/Seder Nezikin/Jerusalem Talmud Avodah Zarah/Daf 2/Halakhah 1",
"id": "Talmud.Yerushalmi.Seder_Nezikin.Jerusalem_Talmud_Avodah_Zarah.2.1",
"children": []}]},

{"title": "Daf 3",
"key": "Talmud/Yerushalmi/Seder Nezikin/Jerusalem Talmud Avodah Zarah/Daf 3",
"id": "Talmud.Yerushalmi.Seder_Nezikin.Jerusalem_Talmud_Avodah_Zarah.3",
"children": [

{"title": "Halakhah 1",
"key": "Talmud/Yerushalmi/Seder Nezikin/Jerusalem Talmud Avodah Zarah/Daf 3/Halakhah 1",
"id": "Talmud.Yerushalmi.Seder_Nezikin.Jerusalem_Talmud_Avodah_Zarah.3.1",
"children": []}]},

{"title": "Daf 4",
"key": "Talmud/Yerushalmi/Seder Nezikin/Jerusalem Talmud Avodah Zarah/Daf 4",
"id": "Talmud.Yerushalmi.Seder_Nezikin.Jerusalem_Talmud_Avodah_Zarah.4",
"children": [

{"title": "Halakhah 1",
"key": "Talmud/Yerushalmi/Seder Nezikin/Jerusalem Talmud Avodah Zarah/Daf 4/Halakhah 1",
"id": "Talmud.Yerushalmi.Seder_Nezikin.Jerusalem_Talmud_Avodah_Zarah.4.1",
"children": []},

{"title": "Halakhah 2",
"key": "Talmud/Yerushalmi/Seder Nezikin/Jerusalem Talmud Avodah Zarah/Daf 4/Halakhah 2",
"id": "Talmud.Yerushalmi.Seder_Nezikin.Jerusalem_Talmud_Avodah_Zarah.4.2",
"children": []},

{"title": "Halakhah 3",
"key": "Talmud/Yerushalmi/Seder Nezikin/Jerusalem Talmud Avodah Zarah/Daf 4/Halakhah 3",
"id": "Talmud.Yerushalmi.Seder_Nezikin.Jerusalem_Talmud_Avodah_Zarah.4.3",
"children": []}]},

{"title": "Daf 5",
"key": "Talmud/Yerushalmi/Seder Nezikin/Jerusalem Talmud Avodah Zarah/Daf 5",
"id": "Talmud.Yerushalmi.Seder_Nezikin.Jerusalem_Talmud_Avodah_Zarah.5",
"children": [

{"title": "Halakhah 1",
"key": "Talmud/Yerushalmi/Seder Nezikin/Jerusalem Talmud Avodah Zarah/Daf 5/Halakhah 1",
"id": "Talmud.Yerushalmi.Seder_Nezikin.Jerusalem_Talmud_Avodah_Zarah.5.1",
"children": []}]},

{"title": "Daf 6",
"key": "Talmud/Yerushalmi/Seder Nezikin/Jerusalem Talmud Avodah Zarah/Daf 6",
"id": "Talmud.Yerushalmi.Seder_Nezikin.Jerusalem_Talmud_Avodah_Zarah.6",
"children": [

{"title": "Halakhah 1",
"key": "Talmud/Yerushalmi/Seder Nezikin/Jerusalem Talmud Avodah Zarah/Daf 6/Halakhah 1",
"id": "Talmud.Yerushalmi.Seder_Nezikin.Jerusalem_Talmud_Avodah_Zarah.6.1",
"children": []},

{"title": "Halakhah 2",
"key": "Talmud/Yerushalmi/Seder Nezikin/Jerusalem Talmud Avodah Zarah/Daf 6/Halakhah 2",
"id": "Talmud.Yerushalmi.Seder_Nezikin.Jerusalem_Talmud_Avodah_Zarah.6.2",
"children": []},

{"title": "Halakhah 3",
"key": "Talmud/Yerushalmi/Seder Nezikin/Jerusalem Talmud Avodah Zarah/Daf 6/Halakhah 3",
"id": "Talmud.Yerushalmi.Seder_Nezikin.Jerusalem_Talmud_Avodah_Zarah.6.3",
"children": []}]},

{"title": "Daf 7",
"key": "Talmud/Yerushalmi/Seder Nezikin/Jerusalem Talmud Avodah Zarah/Daf 7",
"id": "Talmud.Yerushalmi.Seder_Nezikin.Jerusalem_Talmud_Avodah_Zarah.7",
"children": [

{"title": "Halakhah 1",
"key": "Talmud/Yerushalmi/Seder Nezikin/Jerusalem Talmud Avodah Zarah/Daf 7/Halakhah 1",
"id": "Talmud.Yerushalmi.Seder_Nezikin.Jerusalem_Talmud_Avodah_Zarah.7.1",
"children": []},

{"title": "Halakhah 2",
"key": "Talmud/Yerushalmi/Seder Nezikin/Jerusalem Talmud Avodah Zarah/Daf 7/Halakhah 2",
"id": "Talmud.Yerushalmi.Seder_Nezikin.Jerusalem_Talmud_Avodah_Zarah.7.2",
"children": []},

{"title": "Halakhah 3",
"key": "Talmud/Yerushalmi/Seder Nezikin/Jerusalem Talmud Avodah Zarah/Daf 7/Halakhah 3",
"id": "Talmud.Yerushalmi.Seder_Nezikin.Jerusalem_Talmud_Avodah_Zarah.7.3",
"children": []}]},

{"title": "Daf 8",
"key": "Talmud/Yerushalmi/Seder Nezikin/Jerusalem Talmud Avodah Zarah/Daf 8",
"id": "Talmud.Yerushalmi.Seder_Nezikin.Jerusalem_Talmud_Avodah_Zarah.8",
"children": [

{"title": "Halakhah 1",
"key": "Talmud/Yerushalmi/Seder Nezikin/Jerusalem Talmud Avodah Zarah/Daf 8/Halakhah 1",
"id": "Talmud.Yerushalmi.Seder_Nezikin.Jerusalem_Talmud_Avodah_Zarah.8.1",
"children": []}]},

{"title": "Daf 9",
"key": "Talmud/Yerushalmi/Seder Nezikin/Jerusalem Talmud Avodah Zarah/Daf 9",
"id": "Talmud.Yerushalmi.Seder_Nezikin.Jerusalem_Talmud_Avodah_Zarah.9",
"children": [

{"title": "Halakhah 1",
"key": "Talmud/Yerushalmi/Seder Nezikin/Jerusalem Talmud Avodah Zarah/Daf 9/Halakhah 1",
"id": "Talmud.Yerushalmi.Seder_Nezikin.Jerusalem_Talmud_Avodah_Zarah.9.1",
"children": []}]},

{"title": "Daf 10",
"key": "Talmud/Yerushalmi/Seder Nezikin/Jerusalem Talmud Avodah Zarah/Daf 10",
"id": "Talmud.Yerushalmi.Seder_Nezikin.Jerusalem_Talmud_Avodah_Zarah.10",
"children": [

{"title": "Halakhah 1",
"key": "Talmud/Yerushalmi/Seder Nezikin/Jerusalem Talmud Avodah Zarah/Daf 10/Halakhah 1",
"id": "Talmud.Yerushalmi.Seder_Nezikin.Jerusalem_Talmud_Avodah_Zarah.10.1",
"children": []},

{"title": "Halakhah 2",
"key": "Talmud/Yerushalmi/Seder Nezikin/Jerusalem Talmud Avodah Zarah/Daf 10/Halakhah 2",
"id": "Talmud.Yerushalmi.Seder_Nezikin.Jerusalem_Talmud_Avodah_Zarah.10.2",
"children": []}]},

{"title": "Daf 11",
"key": "Talmud/Yerushalmi/Seder Nezikin/Jerusalem Talmud Avodah Zarah/Daf 11",
"id": "Talmud.Yerushalmi.Seder_Nezikin.Jerusalem_Talmud_Avodah_Zarah.11",
"children": [

{"title": "Halakhah 1",
"key": "Talmud/Yerushalmi/Seder Nezikin/Jerusalem Talmud Avodah Zarah/Daf 11/Halakhah 1",
"id": "Talmud.Yerushalmi.Seder_Nezikin.Jerusalem_Talmud_Avodah_Zarah.11.1",
"children": []},

{"title": "Halakhah 2",
"key": "Talmud/Yerushalmi/Seder Nezikin/Jerusalem Talmud Avodah Zarah/Daf 11/Halakhah 2",
"id": "Talmud.Yerushalmi.Seder_Nezikin.Jerusalem_Talmud_Avodah_Zarah.11.2",
"children": []}]},

{"title": "Daf 12",
"key": "Talmud/Yerushalmi/Seder Nezikin/Jerusalem Talmud Avodah Zarah/Daf 12",
"id": "Talmud.Yerushalmi.Seder_Nezikin.Jerusalem_Talmud_Avodah_Zarah.12",
"children": [

{"title": "Halakhah 1",
"key": "Talmud/Yerushalmi/Seder Nezikin/Jerusalem Talmud Avodah Zarah/Daf 12/Halakhah 1",
"id": "Talmud.Yerushalmi.Seder_Nezikin.Jerusalem_Talmud_Avodah_Zarah.12.1",
"children": []}]},

{"title": "Daf 13",
"key": "Talmud/Yerushalmi/Seder Nezikin/Jerusalem Talmud Avodah Zarah/Daf 13",
"id": "Talmud.Yerushalmi.Seder_Nezikin.Jerusalem_Talmud_Avodah_Zarah.13",
"children": [

{"title": "Halakhah 1",
"key": "Talmud/Yerushalmi/Seder Nezikin/Jerusalem Talmud Avodah Zarah/Daf 13/Halakhah 1",
"id": "Talmud.Yerushalmi.Seder_Nezikin.Jerusalem_Talmud_Avodah_Zarah.13.1",
"children": []},

{"title": "Halakhah 2",
"key": "Talmud/Yerushalmi/Seder Nezikin/Jerusalem Talmud Avodah Zarah/Daf 13/Halakhah 2",
"id": "Talmud.Yerushalmi.Seder_Nezikin.Jerusalem_Talmud_Avodah_Zarah.13.2",
"children": []},

{"title": "Halakhah 3",
"key": "Talmud/Yerushalmi/Seder Nezikin/Jerusalem Talmud Avodah Zarah/Daf 13/Halakhah 3",
"id": "Talmud.Yerushalmi.Seder_Nezikin.Jerusalem_Talmud_Avodah_Zarah.13.3",
"children": []},

{"title": "Halakhah 4",
"key": "Talmud/Yerushalmi/Seder Nezikin/Jerusalem Talmud Avodah Zarah/Daf 13/Halakhah 4",
"id": "Talmud.Yerushalmi.Seder_Nezikin.Jerusalem_Talmud_Avodah_Zarah.13.4",
"children": []},

{"title": "Halakhah 5",
"key": "Talmud/Yerushalmi/Seder Nezikin/Jerusalem Talmud Avodah Zarah/Daf 13/Halakhah 5",
"id": "Talmud.Yerushalmi.Seder_Nezikin.Jerusalem_Talmud_Avodah_Zarah.13.5",
"children": []}]},

{"title": "Daf 14",
"key": "Talmud/Yerushalmi/Seder Nezikin/Jerusalem Talmud Avodah Zarah/Daf 14",
"id": "Talmud.Yerushalmi.Seder_Nezikin.Jerusalem_Talmud_Avodah_Zarah.14",
"children": [

{"title": "Halakhah 1",
"key": "Talmud/Yerushalmi/Seder Nezikin/Jerusalem Talmud Avodah Zarah/Daf 14/Halakhah 1",
"id": "Talmud.Yerushalmi.Seder_Nezikin.Jerusalem_Talmud_Avodah_Zarah.14.1",
"children": []},

{"title": "Halakhah 2",
"key": "Talmud/Yerushalmi/Seder Nezikin/Jerusalem Talmud Avodah Zarah/Daf 14/Halakhah 2",
"id": "Talmud.Yerushalmi.Seder_Nezikin.Jerusalem_Talmud_Avodah_Zarah.14.2",
"children": []}]},

{"title": "Daf 15",
"key": "Talmud/Yerushalmi/Seder Nezikin/Jerusalem Talmud Avodah Zarah/Daf 15",
"id": "Talmud.Yerushalmi.Seder_Nezikin.Jerusalem_Talmud_Avodah_Zarah.15",
"children": [

{"title": "Halakhah 1",
"key": "Talmud/Yerushalmi/Seder Nezikin/Jerusalem Talmud Avodah Zarah/Daf 15/Halakhah 1",
"id": "Talmud.Yerushalmi.Seder_Nezikin.Jerusalem_Talmud_Avodah_Zarah.15.1",
"children": []},

{"title": "Halakhah 2",
"key": "Talmud/Yerushalmi/Seder Nezikin/Jerusalem Talmud Avodah Zarah/Daf 15/Halakhah 2",
"id": "Talmud.Yerushalmi.Seder_Nezikin.Jerusalem_Talmud_Avodah_Zarah.15.2",
"children": []},

{"title": "Halakhah 3",
"key": "Talmud/Yerushalmi/Seder Nezikin/Jerusalem Talmud Avodah Zarah/Daf 15/Halakhah 3",
"id": "Talmud.Yerushalmi.Seder_Nezikin.Jerusalem_Talmud_Avodah_Zarah.15.3",
"children": []}]},

{"title": "Daf 16",
"key": "Talmud/Yerushalmi/Seder Nezikin/Jerusalem Talmud Avodah Zarah/Daf 16",
"id": "Talmud.Yerushalmi.Seder_Nezikin.Jerusalem_Talmud_Avodah_Zarah.16",
"children": [

{"title": "Halakhah 1",
"key": "Talmud/Yerushalmi/Seder Nezikin/Jerusalem Talmud Avodah Zarah/Daf 16/Halakhah 1",
"id": "Talmud.Yerushalmi.Seder_Nezikin.Jerusalem_Talmud_Avodah_Zarah.16.1",
"children": []},

{"title": "Halakhah 2",
"key": "Talmud/Yerushalmi/Seder Nezikin/Jerusalem Talmud Avodah Zarah/Daf 16/Halakhah 2",
"id": "Talmud.Yerushalmi.Seder_Nezikin.Jerusalem_Talmud_Avodah_Zarah.16.2",
"children": []},

{"title": "Halakhah 3",
"key": "Talmud/Yerushalmi/Seder Nezikin/Jerusalem Talmud Avodah Zarah/Daf 16/Halakhah 3",
"id": "Talmud.Yerushalmi.Seder_Nezikin.Jerusalem_Talmud_Avodah_Zarah.16.3",
"children": []}]},

{"title": "Daf 17",
"key": "Talmud/Yerushalmi/Seder Nezikin/Jerusalem Talmud Avodah Zarah/Daf 17",
"id": "Talmud.Yerushalmi.Seder_Nezikin.Jerusalem_Talmud_Avodah_Zarah.17",
"children": [

{"title": "Halakhah 1",
"key": "Talmud/Yerushalmi/Seder Nezikin/Jerusalem Talmud Avodah Zarah/Daf 17/Halakhah 1",
"id": "Talmud.Yerushalmi.Seder_Nezikin.Jerusalem_Talmud_Avodah_Zarah.17.1",
"children": []}]},

{"title": "Daf 18",
"key": "Talmud/Yerushalmi/Seder Nezikin/Jerusalem Talmud Avodah Zarah/Daf 18",
"id": "Talmud.Yerushalmi.Seder_Nezikin.Jerusalem_Talmud_Avodah_Zarah.18",
"children": [

{"title": "Halakhah 1",
"key": "Talmud/Yerushalmi/Seder Nezikin/Jerusalem Talmud Avodah Zarah/Daf 18/Halakhah 1",
"id": "Talmud.Yerushalmi.Seder_Nezikin.Jerusalem_Talmud_Avodah_Zarah.18.1",
"children": []}]},

{"title": "Daf 19",
"key": "Talmud/Yerushalmi/Seder Nezikin/Jerusalem Talmud Avodah Zarah/Daf 19",
"id": "Talmud.Yerushalmi.Seder_Nezikin.Jerusalem_Talmud_Avodah_Zarah.19",
"children": [

{"title": "Halakhah 1",
"key": "Talmud/Yerushalmi/Seder Nezikin/Jerusalem Talmud Avodah Zarah/Daf 19/Halakhah 1",
"id": "Talmud.Yerushalmi.Seder_Nezikin.Jerusalem_Talmud_Avodah_Zarah.19.1",
"children": []},

{"title": "Halakhah 2",
"key": "Talmud/Yerushalmi/Seder Nezikin/Jerusalem Talmud Avodah Zarah/Daf 19/Halakhah 2",
"id": "Talmud.Yerushalmi.Seder_Nezikin.Jerusalem_Talmud_Avodah_Zarah.19.2",
"children": []},

{"title": "Halakhah 3",
"key": "Talmud/Yerushalmi/Seder Nezikin/Jerusalem Talmud Avodah Zarah/Daf 19/Halakhah 3",
"id": "Talmud.Yerushalmi.Seder_Nezikin.Jerusalem_Talmud_Avodah_Zarah.19.3",
"children": []}]},

{"title": "Daf 20",
"key": "Talmud/Yerushalmi/Seder Nezikin/Jerusalem Talmud Avodah Zarah/Daf 20",
"id": "Talmud.Yerushalmi.Seder_Nezikin.Jerusalem_Talmud_Avodah_Zarah.20",
"children": [

{"title": "Halakhah 1",
"key": "Talmud/Yerushalmi/Seder Nezikin/Jerusalem Talmud Avodah Zarah/Daf 20/Halakhah 1",
"id": "Talmud.Yerushalmi.Seder_Nezikin.Jerusalem_Talmud_Avodah_Zarah.20.1",
"children": []}]},

{"title": "Daf 21",
"key": "Talmud/Yerushalmi/Seder Nezikin/Jerusalem Talmud Avodah Zarah/Daf 21",
"id": "Talmud.Yerushalmi.Seder_Nezikin.Jerusalem_Talmud_Avodah_Zarah.21",
"children": [

{"title": "Halakhah 1",
"key": "Talmud/Yerushalmi/Seder Nezikin/Jerusalem Talmud Avodah Zarah/Daf 21/Halakhah 1",
"id": "Talmud.Yerushalmi.Seder_Nezikin.Jerusalem_Talmud_Avodah_Zarah.21.1",
"children": []}]},

{"title": "Daf 22",
"key": "Talmud/Yerushalmi/Seder Nezikin/Jerusalem Talmud Avodah Zarah/Daf 22",
"id": "Talmud.Yerushalmi.Seder_Nezikin.Jerusalem_Talmud_Avodah_Zarah.22",
"children": [

{"title": "Halakhah 1",
"key": "Talmud/Yerushalmi/Seder Nezikin/Jerusalem Talmud Avodah Zarah/Daf 22/Halakhah 1",
"id": "Talmud.Yerushalmi.Seder_Nezikin.Jerusalem_Talmud_Avodah_Zarah.22.1",
"children": []},

{"title": "Halakhah 2",
"key": "Talmud/Yerushalmi/Seder Nezikin/Jerusalem Talmud Avodah Zarah/Daf 22/Halakhah 2",
"id": "Talmud.Yerushalmi.Seder_Nezikin.Jerusalem_Talmud_Avodah_Zarah.22.2",
"children": []},

{"title": "Halakhah 3",
"key": "Talmud/Yerushalmi/Seder Nezikin/Jerusalem Talmud Avodah Zarah/Daf 22/Halakhah 3",
"id": "Talmud.Yerushalmi.Seder_Nezikin.Jerusalem_Talmud_Avodah_Zarah.22.3",
"children": []}]},

{"title": "Daf 23",
"key": "Talmud/Yerushalmi/Seder Nezikin/Jerusalem Talmud Avodah Zarah/Daf 23",
"id": "Talmud.Yerushalmi.Seder_Nezikin.Jerusalem_Talmud_Avodah_Zarah.23",
"children": [

{"title": "Halakhah 1",
"key": "Talmud/Yerushalmi/Seder Nezikin/Jerusalem Talmud Avodah Zarah/Daf 23/Halakhah 1",
"id": "Talmud.Yerushalmi.Seder_Nezikin.Jerusalem_Talmud_Avodah_Zarah.23.1",
"children": []}]},

{"title": "Daf 24",
"key": "Talmud/Yerushalmi/Seder Nezikin/Jerusalem Talmud Avodah Zarah/Daf 24",
"id": "Talmud.Yerushalmi.Seder_Nezikin.Jerusalem_Talmud_Avodah_Zarah.24",
"children": [

{"title": "Halakhah 1",
"key": "Talmud/Yerushalmi/Seder Nezikin/Jerusalem Talmud Avodah Zarah/Daf 24/Halakhah 1",
"id": "Talmud.Yerushalmi.Seder_Nezikin.Jerusalem_Talmud_Avodah_Zarah.24.1",
"children": []}]},

{"title": "Daf 25",
"key": "Talmud/Yerushalmi/Seder Nezikin/Jerusalem Talmud Avodah Zarah/Daf 25",
"id": "Talmud.Yerushalmi.Seder_Nezikin.Jerusalem_Talmud_Avodah_Zarah.25",
"children": [

{"title": "Halakhah 1",
"key": "Talmud/Yerushalmi/Seder Nezikin/Jerusalem Talmud Avodah Zarah/Daf 25/Halakhah 1",
"id": "Talmud.Yerushalmi.Seder_Nezikin.Jerusalem_Talmud_Avodah_Zarah.25.1",
"children": []},

{"title": "Halakhah 2",
"key": "Talmud/Yerushalmi/Seder Nezikin/Jerusalem Talmud Avodah Zarah/Daf 25/Halakhah 2",
"id": "Talmud.Yerushalmi.Seder_Nezikin.Jerusalem_Talmud_Avodah_Zarah.25.2",
"children": []},

{"title": "Halakhah 3",
"key": "Talmud/Yerushalmi/Seder Nezikin/Jerusalem Talmud Avodah Zarah/Daf 25/Halakhah 3",
"id": "Talmud.Yerushalmi.Seder_Nezikin.Jerusalem_Talmud_Avodah_Zarah.25.3",
"children": []}]},

{"title": "Daf 26",
"key": "Talmud/Yerushalmi/Seder Nezikin/Jerusalem Talmud Avodah Zarah/Daf 26",
"id": "Talmud.Yerushalmi.Seder_Nezikin.Jerusalem_Talmud_Avodah_Zarah.26",
"children": [

{"title": "Halakhah 1",
"key": "Talmud/Yerushalmi/Seder Nezikin/Jerusalem Talmud Avodah Zarah/Daf 26/Halakhah 1",
"id": "Talmud.Yerushalmi.Seder_Nezikin.Jerusalem_Talmud_Avodah_Zarah.26.1",
"children": []}]},

{"title": "Daf 27",
"key": "Talmud/Yerushalmi/Seder Nezikin/Jerusalem Talmud Avodah Zarah/Daf 27",
"id": "Talmud.Yerushalmi.Seder_Nezikin.Jerusalem_Talmud_Avodah_Zarah.27",
"children": [

{"title": "Halakhah 1",
"key": "Talmud/Yerushalmi/Seder Nezikin/Jerusalem Talmud Avodah Zarah/Daf 27/Halakhah 1",
"id": "Talmud.Yerushalmi.Seder_Nezikin.Jerusalem_Talmud_Avodah_Zarah.27.1",
"children": []},

{"title": "Halakhah 2",
"key": "Talmud/Yerushalmi/Seder Nezikin/Jerusalem Talmud Avodah Zarah/Daf 27/Halakhah 2",
"id": "Talmud.Yerushalmi.Seder_Nezikin.Jerusalem_Talmud_Avodah_Zarah.27.2",
"children": []},

{"title": "Halakhah 3",
"key": "Talmud/Yerushalmi/Seder Nezikin/Jerusalem Talmud Avodah Zarah/Daf 27/Halakhah 3",
"id": "Talmud.Yerushalmi.Seder_Nezikin.Jerusalem_Talmud_Avodah_Zarah.27.3",
"children": []},

{"title": "Halakhah 4",
"key": "Talmud/Yerushalmi/Seder Nezikin/Jerusalem Talmud Avodah Zarah/Daf 27/Halakhah 4",
"id": "Talmud.Yerushalmi.Seder_Nezikin.Jerusalem_Talmud_Avodah_Zarah.27.4",
"children": []},

{"title": "Halakhah 5",
"key": "Talmud/Yerushalmi/Seder Nezikin/Jerusalem Talmud Avodah Zarah/Daf 27/Halakhah 5",
"id": "Talmud.Yerushalmi.Seder_Nezikin.Jerusalem_Talmud_Avodah_Zarah.27.5",
"children": []},

{"title": "Halakhah 6",
"key": "Talmud/Yerushalmi/Seder Nezikin/Jerusalem Talmud Avodah Zarah/Daf 27/Halakhah 6",
"id": "Talmud.Yerushalmi.Seder_Nezikin.Jerusalem_Talmud_Avodah_Zarah.27.6",
"children": []}]},

{"title": "Daf 28",
"key": "Talmud/Yerushalmi/Seder Nezikin/Jerusalem Talmud Avodah Zarah/Daf 28",
"id": "Talmud.Yerushalmi.Seder_Nezikin.Jerusalem_Talmud_Avodah_Zarah.28",
"children": [

{"title": "Halakhah 1",
"key": "Talmud/Yerushalmi/Seder Nezikin/Jerusalem Talmud Avodah Zarah/Daf 28/Halakhah 1",
"id": "Talmud.Yerushalmi.Seder_Nezikin.Jerusalem_Talmud_Avodah_Zarah.28.1",
"children": []},

{"title": "Halakhah 2",
"key": "Talmud/Yerushalmi/Seder Nezikin/Jerusalem Talmud Avodah Zarah/Daf 28/Halakhah 2",
"id": "Talmud.Yerushalmi.Seder_Nezikin.Jerusalem_Talmud_Avodah_Zarah.28.2",
"children": []}]},

{"title": "Daf 29",
"key": "Talmud/Yerushalmi/Seder Nezikin/Jerusalem Talmud Avodah Zarah/Daf 29",
"id": "Talmud.Yerushalmi.Seder_Nezikin.Jerusalem_Talmud_Avodah_Zarah.29",
"children": [

{"title": "Halakhah 1",
"key": "Talmud/Yerushalmi/Seder Nezikin/Jerusalem Talmud Avodah Zarah/Daf 29/Halakhah 1",
"id": "Talmud.Yerushalmi.Seder_Nezikin.Jerusalem_Talmud_Avodah_Zarah.29.1",
"children": []}]},

{"title": "Daf 30",
"key": "Talmud/Yerushalmi/Seder Nezikin/Jerusalem Talmud Avodah Zarah/Daf 30",
"id": "Talmud.Yerushalmi.Seder_Nezikin.Jerusalem_Talmud_Avodah_Zarah.30",
"children": [

{"title": "Halakhah 1",
"key": "Talmud/Yerushalmi/Seder Nezikin/Jerusalem Talmud Avodah Zarah/Daf 30/Halakhah 1",
"id": "Talmud.Yerushalmi.Seder_Nezikin.Jerusalem_Talmud_Avodah_Zarah.30.1",
"children": []},

{"title": "Halakhah 2",
"key": "Talmud/Yerushalmi/Seder Nezikin/Jerusalem Talmud Avodah Zarah/Daf 30/Halakhah 2",
"id": "Talmud.Yerushalmi.Seder_Nezikin.Jerusalem_Talmud_Avodah_Zarah.30.2",
"children": []},

{"title": "Halakhah 3",
"key": "Talmud/Yerushalmi/Seder Nezikin/Jerusalem Talmud Avodah Zarah/Daf 30/Halakhah 3",
"id": "Talmud.Yerushalmi.Seder_Nezikin.Jerusalem_Talmud_Avodah_Zarah.30.3",
"children": []}]},

{"title": "Daf 31",
"key": "Talmud/Yerushalmi/Seder Nezikin/Jerusalem Talmud Avodah Zarah/Daf 31",
"id": "Talmud.Yerushalmi.Seder_Nezikin.Jerusalem_Talmud_Avodah_Zarah.31",
"children": [

{"title": "Halakhah 1",
"key": "Talmud/Yerushalmi/Seder Nezikin/Jerusalem Talmud Avodah Zarah/Daf 31/Halakhah 1",
"id": "Talmud.Yerushalmi.Seder_Nezikin.Jerusalem_Talmud_Avodah_Zarah.31.1",
"children": []}]},

{"title": "Daf 32",
"key": "Talmud/Yerushalmi/Seder Nezikin/Jerusalem Talmud Avodah Zarah/Daf 32",
"id": "Talmud.Yerushalmi.Seder_Nezikin.Jerusalem_Talmud_Avodah_Zarah.32",
"children": [

{"title": "Halakhah 1",
"key": "Talmud/Yerushalmi/Seder Nezikin/Jerusalem Talmud Avodah Zarah/Daf 32/Halakhah 1",
"id": "Talmud.Yerushalmi.Seder_Nezikin.Jerusalem_Talmud_Avodah_Zarah.32.1",
"children": []},

{"title": "Halakhah 2",
"key": "Talmud/Yerushalmi/Seder Nezikin/Jerusalem Talmud Avodah Zarah/Daf 32/Halakhah 2",
"id": "Talmud.Yerushalmi.Seder_Nezikin.Jerusalem_Talmud_Avodah_Zarah.32.2",
"children": []},

{"title": "Halakhah 3",
"key": "Talmud/Yerushalmi/Seder Nezikin/Jerusalem Talmud Avodah Zarah/Daf 32/Halakhah 3",
"id": "Talmud.Yerushalmi.Seder_Nezikin.Jerusalem_Talmud_Avodah_Zarah.32.3",
"children": []}]},

{"title": "Daf 33",
"key": "Talmud/Yerushalmi/Seder Nezikin/Jerusalem Talmud Avodah Zarah/Daf 33",
"id": "Talmud.Yerushalmi.Seder_Nezikin.Jerusalem_Talmud_Avodah_Zarah.33",
"children": [

{"title": "Halakhah 1",
"key": "Talmud/Yerushalmi/Seder Nezikin/Jerusalem Talmud Avodah Zarah/Daf 33/Halakhah 1",
"id": "Talmud.Yerushalmi.Seder_Nezikin.Jerusalem_Talmud_Avodah_Zarah.33.1",
"children": []}]},

{"title": "Daf 34",
"key": "Talmud/Yerushalmi/Seder Nezikin/Jerusalem Talmud Avodah Zarah/Daf 34",
"id": "Talmud.Yerushalmi.Seder_Nezikin.Jerusalem_Talmud_Avodah_Zarah.34",
"children": [

{"title": "Halakhah 1",
"key": "Talmud/Yerushalmi/Seder Nezikin/Jerusalem Talmud Avodah Zarah/Daf 34/Halakhah 1",
"id": "Talmud.Yerushalmi.Seder_Nezikin.Jerusalem_Talmud_Avodah_Zarah.34.1",
"children": []}]},

{"title": "Daf 35",
"key": "Talmud/Yerushalmi/Seder Nezikin/Jerusalem Talmud Avodah Zarah/Daf 35",
"id": "Talmud.Yerushalmi.Seder_Nezikin.Jerusalem_Talmud_Avodah_Zarah.35",
"children": [

{"title": "Halakhah 1",
"key": "Talmud/Yerushalmi/Seder Nezikin/Jerusalem Talmud Avodah Zarah/Daf 35/Halakhah 1",
"id": "Talmud.Yerushalmi.Seder_Nezikin.Jerusalem_Talmud_Avodah_Zarah.35.1",
"children": []},

{"title": "Halakhah 2",
"key": "Talmud/Yerushalmi/Seder Nezikin/Jerusalem Talmud Avodah Zarah/Daf 35/Halakhah 2",
"id": "Talmud.Yerushalmi.Seder_Nezikin.Jerusalem_Talmud_Avodah_Zarah.35.2",
"children": []},

{"title": "Halakhah 3",
"key": "Talmud/Yerushalmi/Seder Nezikin/Jerusalem Talmud Avodah Zarah/Daf 35/Halakhah 3",
"id": "Talmud.Yerushalmi.Seder_Nezikin.Jerusalem_Talmud_Avodah_Zarah.35.3",
"children": []}]},

{"title": "Daf 36",
"key": "Talmud/Yerushalmi/Seder Nezikin/Jerusalem Talmud Avodah Zarah/Daf 36",
"id": "Talmud.Yerushalmi.Seder_Nezikin.Jerusalem_Talmud_Avodah_Zarah.36",
"children": [

{"title": "Halakhah 1",
"key": "Talmud/Yerushalmi/Seder Nezikin/Jerusalem Talmud Avodah Zarah/Daf 36/Halakhah 1",
"id": "Talmud.Yerushalmi.Seder_Nezikin.Jerusalem_Talmud_Avodah_Zarah.36.1",
"children": []},

{"title": "Halakhah 2",
"key": "Talmud/Yerushalmi/Seder Nezikin/Jerusalem Talmud Avodah Zarah/Daf 36/Halakhah 2",
"id": "Talmud.Yerushalmi.Seder_Nezikin.Jerusalem_Talmud_Avodah_Zarah.36.2",
"children": []},

{"title": "Halakhah 3",
"key": "Talmud/Yerushalmi/Seder Nezikin/Jerusalem Talmud Avodah Zarah/Daf 36/Halakhah 3",
"id": "Talmud.Yerushalmi.Seder_Nezikin.Jerusalem_Talmud_Avodah_Zarah.36.3",
"children": []}]},

{"title": "Daf 37",
"key": "Talmud/Yerushalmi/Seder Nezikin/Jerusalem Talmud Avodah Zarah/Daf 37",
"id": "Talmud.Yerushalmi.Seder_Nezikin.Jerusalem_Talmud_Avodah_Zarah.37",
"children": [

{"title": "Halakhah 1",
"key": "Talmud/Yerushalmi/Seder Nezikin/Jerusalem Talmud Avodah Zarah/Daf 37/Halakhah 1",
"id": "Talmud.Yerushalmi.Seder_Nezikin.Jerusalem_Talmud_Avodah_Zarah.37.1",
"children": []},

{"title": "Halakhah 2",
"key": "Talmud/Yerushalmi/Seder Nezikin/Jerusalem Talmud Avodah Zarah/Daf 37/Halakhah 2",
"id": "Talmud.Yerushalmi.Seder_Nezikin.Jerusalem_Talmud_Avodah_Zarah.37.2",
"children": []},

{"title": "Halakhah 3",
"key": "Talmud/Yerushalmi/Seder Nezikin/Jerusalem Talmud Avodah Zarah/Daf 37/Halakhah 3",
"id": "Talmud.Yerushalmi.Seder_Nezikin.Jerusalem_Talmud_Avodah_Zarah.37.3",
"children": []}]},

{"title": "Daf 38",
"key": "Talmud/Yerushalmi/Seder Nezikin/Jerusalem Talmud Avodah Zarah/Daf 38",
"id": "Talmud.Yerushalmi.Seder_Nezikin.Jerusalem_Talmud_Avodah_Zarah.38",
"children": [

{"title": "Halakhah 1",
"key": "Talmud/Yerushalmi/Seder Nezikin/Jerusalem Talmud Avodah Zarah/Daf 38/Halakhah 1",
"id": "Talmud.Yerushalmi.Seder_Nezikin.Jerusalem_Talmud_Avodah_Zarah.38.1",
"children": []},

{"title": "Halakhah 2",
"key": "Talmud/Yerushalmi/Seder Nezikin/Jerusalem Talmud Avodah Zarah/Daf 38/Halakhah 2",
"id": "Talmud.Yerushalmi.Seder_Nezikin.Jerusalem_Talmud_Avodah_Zarah.38.2",
"children": []},

{"title": "Halakhah 3",
"key": "Talmud/Yerushalmi/Seder Nezikin/Jerusalem Talmud Avodah Zarah/Daf 38/Halakhah 3",
"id": "Talmud.Yerushalmi.Seder_Nezikin.Jerusalem_Talmud_Avodah_Zarah.38.3",
"children": []}]},

{"title": "Daf 39",
"key": "Talmud/Yerushalmi/Seder Nezikin/Jerusalem Talmud Avodah Zarah/Daf 39",
"id": "Talmud.Yerushalmi.Seder_Nezikin.Jerusalem_Talmud_Avodah_Zarah.39",
"children": [

{"title": "Halakhah 1",
"key": "Talmud/Yerushalmi/Seder Nezikin/Jerusalem Talmud Avodah Zarah/Daf 39/Halakhah 1",
"id": "Talmud.Yerushalmi.Seder_Nezikin.Jerusalem_Talmud_Avodah_Zarah.39.1",
"children": []},

{"title": "Halakhah 2",
"key": "Talmud/Yerushalmi/Seder Nezikin/Jerusalem Talmud Avodah Zarah/Daf 39/Halakhah 2",
"id": "Talmud.Yerushalmi.Seder_Nezikin.Jerusalem_Talmud_Avodah_Zarah.39.2",
"children": []},

{"title": "Halakhah 3",
"key": "Talmud/Yerushalmi/Seder Nezikin/Jerusalem Talmud Avodah Zarah/Daf 39/Halakhah 3",
"id": "Talmud.Yerushalmi.Seder_Nezikin.Jerusalem_Talmud_Avodah_Zarah.39.3",
"children": []}]},

{"title": "Daf 40",
"key": "Talmud/Yerushalmi/Seder Nezikin/Jerusalem Talmud Avodah Zarah/Daf 40",
"id": "Talmud.Yerushalmi.Seder_Nezikin.Jerusalem_Talmud_Avodah_Zarah.40",
"children": [

{"title": "Halakhah 1",
"key": "Talmud/Yerushalmi/Seder Nezikin/Jerusalem Talmud Avodah Zarah/Daf 40/Halakhah 1",
"id": "Talmud.Yerushalmi.Seder_Nezikin.Jerusalem_Talmud_Avodah_Zarah.40.1",
"children": []}]},

{"title": "Daf 41",
"key": "Talmud/Yerushalmi/Seder Nezikin/Jerusalem Talmud Avodah Zarah/Daf 41",
"id": "Talmud.Yerushalmi.Seder_Nezikin.Jerusalem_Talmud_Avodah_Zarah.41",
"children": [

{"title": "Halakhah 1",
"key": "Talmud/Yerushalmi/Seder Nezikin/Jerusalem Talmud Avodah Zarah/Daf 41/Halakhah 1",
"id": "Talmud.Yerushalmi.Seder_Nezikin.Jerusalem_Talmud_Avodah_Zarah.41.1",
"children": []}]},

{"title": "Daf 42",
"key": "Talmud/Yerushalmi/Seder Nezikin/Jerusalem Talmud Avodah Zarah/Daf 42",
"id": "Talmud.Yerushalmi.Seder_Nezikin.Jerusalem_Talmud_Avodah_Zarah.42",
"children": [

{"title": "Halakhah 1",
"key": "Talmud/Yerushalmi/Seder Nezikin/Jerusalem Talmud Avodah Zarah/Daf 42/Halakhah 1",
"id": "Talmud.Yerushalmi.Seder_Nezikin.Jerusalem_Talmud_Avodah_Zarah.42.1",
"children": []},

{"title": "Halakhah 2",
"key": "Talmud/Yerushalmi/Seder Nezikin/Jerusalem Talmud Avodah Zarah/Daf 42/Halakhah 2",
"id": "Talmud.Yerushalmi.Seder_Nezikin.Jerusalem_Talmud_Avodah_Zarah.42.2",
"children": []},

{"title": "Halakhah 3",
"key": "Talmud/Yerushalmi/Seder Nezikin/Jerusalem Talmud Avodah Zarah/Daf 42/Halakhah 3",
"id": "Talmud.Yerushalmi.Seder_Nezikin.Jerusalem_Talmud_Avodah_Zarah.42.3",
"children": []}]},

{"title": "Daf 43",
"key": "Talmud/Yerushalmi/Seder Nezikin/Jerusalem Talmud Avodah Zarah/Daf 43",
"id": "Talmud.Yerushalmi.Seder_Nezikin.Jerusalem_Talmud_Avodah_Zarah.43",
"children": [

{"title": "Halakhah 1",
"key": "Talmud/Yerushalmi/Seder Nezikin/Jerusalem Talmud Avodah Zarah/Daf 43/Halakhah 1",
"id": "Talmud.Yerushalmi.Seder_Nezikin.Jerusalem_Talmud_Avodah_Zarah.43.1",
"children": []}]},

{"title": "Daf 44",
"key": "Talmud/Yerushalmi/Seder Nezikin/Jerusalem Talmud Avodah Zarah/Daf 44",
"id": "Talmud.Yerushalmi.Seder_Nezikin.Jerusalem_Talmud_Avodah_Zarah.44",
"children": [

{"title": "Halakhah 1",
"key": "Talmud/Yerushalmi/Seder Nezikin/Jerusalem Talmud Avodah Zarah/Daf 44/Halakhah 1",
"id": "Talmud.Yerushalmi.Seder_Nezikin.Jerusalem_Talmud_Avodah_Zarah.44.1",
"children": []}]},

{"title": "Daf 45",
"key": "Talmud/Yerushalmi/Seder Nezikin/Jerusalem Talmud Avodah Zarah/Daf 45",
"id": "Talmud.Yerushalmi.Seder_Nezikin.Jerusalem_Talmud_Avodah_Zarah.45",
"children": [

{"title": "Halakhah 1",
"key": "Talmud/Yerushalmi/Seder Nezikin/Jerusalem Talmud Avodah Zarah/Daf 45/Halakhah 1",
"id": "Talmud.Yerushalmi.Seder_Nezikin.Jerusalem_Talmud_Avodah_Zarah.45.1",
"children": []},

{"title": "Halakhah 2",
"key": "Talmud/Yerushalmi/Seder Nezikin/Jerusalem Talmud Avodah Zarah/Daf 45/Halakhah 2",
"id": "Talmud.Yerushalmi.Seder_Nezikin.Jerusalem_Talmud_Avodah_Zarah.45.2",
"children": []},

{"title": "Halakhah 3",
"key": "Talmud/Yerushalmi/Seder Nezikin/Jerusalem Talmud Avodah Zarah/Daf 45/Halakhah 3",
"id": "Talmud.Yerushalmi.Seder_Nezikin.Jerusalem_Talmud_Avodah_Zarah.45.3",
"children": []}]},

{"title": "Daf 46",
"key": "Talmud/Yerushalmi/Seder Nezikin/Jerusalem Talmud Avodah Zarah/Daf 46",
"id": "Talmud.Yerushalmi.Seder_Nezikin.Jerusalem_Talmud_Avodah_Zarah.46",
"children": [

{"title": "Halakhah 1",
"key": "Talmud/Yerushalmi/Seder Nezikin/Jerusalem Talmud Avodah Zarah/Daf 46/Halakhah 1",
"id": "Talmud.Yerushalmi.Seder_Nezikin.Jerusalem_Talmud_Avodah_Zarah.46.1",
"children": []},

{"title": "Halakhah 2",
"key": "Talmud/Yerushalmi/Seder Nezikin/Jerusalem Talmud Avodah Zarah/Daf 46/Halakhah 2",
"id": "Talmud.Yerushalmi.Seder_Nezikin.Jerusalem_Talmud_Avodah_Zarah.46.2",
"children": []},

{"title": "Halakhah 3",
"key": "Talmud/Yerushalmi/Seder Nezikin/Jerusalem Talmud Avodah Zarah/Daf 46/Halakhah 3",
"id": "Talmud.Yerushalmi.Seder_Nezikin.Jerusalem_Talmud_Avodah_Zarah.46.3",
"children": []}]},

{"title": "Daf 47",
"key": "Talmud/Yerushalmi/Seder Nezikin/Jerusalem Talmud Avodah Zarah/Daf 47",
"id": "Talmud.Yerushalmi.Seder_Nezikin.Jerusalem_Talmud_Avodah_Zarah.47",
"children": [

{"title": "Halakhah 1",
"key": "Talmud/Yerushalmi/Seder Nezikin/Jerusalem Talmud Avodah Zarah/Daf 47/Halakhah 1",
"id": "Talmud.Yerushalmi.Seder_Nezikin.Jerusalem_Talmud_Avodah_Zarah.47.1",
"children": []},

{"title": "Halakhah 2",
"key": "Talmud/Yerushalmi/Seder Nezikin/Jerusalem Talmud Avodah Zarah/Daf 47/Halakhah 2",
"id": "Talmud.Yerushalmi.Seder_Nezikin.Jerusalem_Talmud_Avodah_Zarah.47.2",
"children": []},

{"title": "Halakhah 3",
"key": "Talmud/Yerushalmi/Seder Nezikin/Jerusalem Talmud Avodah Zarah/Daf 47/Halakhah 3",
"id": "Talmud.Yerushalmi.Seder_Nezikin.Jerusalem_Talmud_Avodah_Zarah.47.3",
"children": []},

{"title": "Halakhah 4",
"key": "Talmud/Yerushalmi/Seder Nezikin/Jerusalem Talmud Avodah Zarah/Daf 47/Halakhah 4",
"id": "Talmud.Yerushalmi.Seder_Nezikin.Jerusalem_Talmud_Avodah_Zarah.47.4",
"children": []},

{"title": "Halakhah 5",
"key": "Talmud/Yerushalmi/Seder Nezikin/Jerusalem Talmud Avodah Zarah/Daf 47/Halakhah 5",
"id": "Talmud.Yerushalmi.Seder_Nezikin.Jerusalem_Talmud_Avodah_Zarah.47.5",
"children": []},

{"title": "Halakhah 6",
"key": "Talmud/Yerushalmi/Seder Nezikin/Jerusalem Talmud Avodah Zarah/Daf 47/Halakhah 6",
"id": "Talmud.Yerushalmi.Seder_Nezikin.Jerusalem_Talmud_Avodah_Zarah.47.6",
"children": []}]},

{"title": "Daf 48",
"key": "Talmud/Yerushalmi/Seder Nezikin/Jerusalem Talmud Avodah Zarah/Daf 48",
"id": "Talmud.Yerushalmi.Seder_Nezikin.Jerusalem_Talmud_Avodah_Zarah.48",
"children": [

{"title": "Halakhah 1",
"key": "Talmud/Yerushalmi/Seder Nezikin/Jerusalem Talmud Avodah Zarah/Daf 48/Halakhah 1",
"id": "Talmud.Yerushalmi.Seder_Nezikin.Jerusalem_Talmud_Avodah_Zarah.48.1",
"children": []},

{"title": "Halakhah 2",
"key": "Talmud/Yerushalmi/Seder Nezikin/Jerusalem Talmud Avodah Zarah/Daf 48/Halakhah 2",
"id": "Talmud.Yerushalmi.Seder_Nezikin.Jerusalem_Talmud_Avodah_Zarah.48.2",
"children": []},

{"title": "Halakhah 3",
"key": "Talmud/Yerushalmi/Seder Nezikin/Jerusalem Talmud Avodah Zarah/Daf 48/Halakhah 3",
"id": "Talmud.Yerushalmi.Seder_Nezikin.Jerusalem_Talmud_Avodah_Zarah.48.3",
"children": []}]},

{"title": "Daf 49",
"key": "Talmud/Yerushalmi/Seder Nezikin/Jerusalem Talmud Avodah Zarah/Daf 49",
"id": "Talmud.Yerushalmi.Seder_Nezikin.Jerusalem_Talmud_Avodah_Zarah.49",
"children": [

{"title": "Halakhah 1",
"key": "Talmud/Yerushalmi/Seder Nezikin/Jerusalem Talmud Avodah Zarah/Daf 49/Halakhah 1",
"id": "Talmud.Yerushalmi.Seder_Nezikin.Jerusalem_Talmud_Avodah_Zarah.49.1",
"children": []},

{"title": "Halakhah 2",
"key": "Talmud/Yerushalmi/Seder Nezikin/Jerusalem Talmud Avodah Zarah/Daf 49/Halakhah 2",
"id": "Talmud.Yerushalmi.Seder_Nezikin.Jerusalem_Talmud_Avodah_Zarah.49.2",
"children": []},

{"title": "Halakhah 3",
"key": "Talmud/Yerushalmi/Seder Nezikin/Jerusalem Talmud Avodah Zarah/Daf 49/Halakhah 3",
"id": "Talmud.Yerushalmi.Seder_Nezikin.Jerusalem_Talmud_Avodah_Zarah.49.3",
"children": []},

{"title": "Halakhah 4",
"key": "Talmud/Yerushalmi/Seder Nezikin/Jerusalem Talmud Avodah Zarah/Daf 49/Halakhah 4",
"id": "Talmud.Yerushalmi.Seder_Nezikin.Jerusalem_Talmud_Avodah_Zarah.49.4",
"children": []},

{"title": "Halakhah 5",
"key": "Talmud/Yerushalmi/Seder Nezikin/Jerusalem Talmud Avodah Zarah/Daf 49/Halakhah 5",
"id": "Talmud.Yerushalmi.Seder_Nezikin.Jerusalem_Talmud_Avodah_Zarah.49.5",
"children": []},

{"title": "Halakhah 6",
"key": "Talmud/Yerushalmi/Seder Nezikin/Jerusalem Talmud Avodah Zarah/Daf 49/Halakhah 6",
"id": "Talmud.Yerushalmi.Seder_Nezikin.Jerusalem_Talmud_Avodah_Zarah.49.6",
"children": []}]},

{"title": "Daf 50",
"key": "Talmud/Yerushalmi/Seder Nezikin/Jerusalem Talmud Avodah Zarah/Daf 50",
"id": "Talmud.Yerushalmi.Seder_Nezikin.Jerusalem_Talmud_Avodah_Zarah.50",
"children": [

{"title": "Halakhah 1",
"key": "Talmud/Yerushalmi/Seder Nezikin/Jerusalem Talmud Avodah Zarah/Daf 50/Halakhah 1",
"id": "Talmud.Yerushalmi.Seder_Nezikin.Jerusalem_Talmud_Avodah_Zarah.50.1",
"children": []}]},

{"title": "Daf 51",
"key": "Talmud/Yerushalmi/Seder Nezikin/Jerusalem Talmud Avodah Zarah/Daf 51",
"id": "Talmud.Yerushalmi.Seder_Nezikin.Jerusalem_Talmud_Avodah_Zarah.51",
"children": [

{"title": "Halakhah 1",
"key": "Talmud/Yerushalmi/Seder Nezikin/Jerusalem Talmud Avodah Zarah/Daf 51/Halakhah 1",
"id": "Talmud.Yerushalmi.Seder_Nezikin.Jerusalem_Talmud_Avodah_Zarah.51.1",
"children": []},

{"title": "Halakhah 2",
"key": "Talmud/Yerushalmi/Seder Nezikin/Jerusalem Talmud Avodah Zarah/Daf 51/Halakhah 2",
"id": "Talmud.Yerushalmi.Seder_Nezikin.Jerusalem_Talmud_Avodah_Zarah.51.2",
"children": []},

{"title": "Halakhah 3",
"key": "Talmud/Yerushalmi/Seder Nezikin/Jerusalem Talmud Avodah Zarah/Daf 51/Halakhah 3",
"id": "Talmud.Yerushalmi.Seder_Nezikin.Jerusalem_Talmud_Avodah_Zarah.51.3",
"children": []}]},

{"title": "Daf 52",
"key": "Talmud/Yerushalmi/Seder Nezikin/Jerusalem Talmud Avodah Zarah/Daf 52",
"id": "Talmud.Yerushalmi.Seder_Nezikin.Jerusalem_Talmud_Avodah_Zarah.52",
"children": [

{"title": "Halakhah 1",
"key": "Talmud/Yerushalmi/Seder Nezikin/Jerusalem Talmud Avodah Zarah/Daf 52/Halakhah 1",
"id": "Talmud.Yerushalmi.Seder_Nezikin.Jerusalem_Talmud_Avodah_Zarah.52.1",
"children": []},

{"title": "Halakhah 2",
"key": "Talmud/Yerushalmi/Seder Nezikin/Jerusalem Talmud Avodah Zarah/Daf 52/Halakhah 2",
"id": "Talmud.Yerushalmi.Seder_Nezikin.Jerusalem_Talmud_Avodah_Zarah.52.2",
"children": []},

{"title": "Halakhah 3",
"key": "Talmud/Yerushalmi/Seder Nezikin/Jerusalem Talmud Avodah Zarah/Daf 52/Halakhah 3",
"id": "Talmud.Yerushalmi.Seder_Nezikin.Jerusalem_Talmud_Avodah_Zarah.52.3",
"children": []},

{"title": "Halakhah 4",
"key": "Talmud/Yerushalmi/Seder Nezikin/Jerusalem Talmud Avodah Zarah/Daf 52/Halakhah 4",
"id": "Talmud.Yerushalmi.Seder_Nezikin.Jerusalem_Talmud_Avodah_Zarah.52.4",
"children": []}]},

{"title": "Daf 53",
"key": "Talmud/Yerushalmi/Seder Nezikin/Jerusalem Talmud Avodah Zarah/Daf 53",
"id": "Talmud.Yerushalmi.Seder_Nezikin.Jerusalem_Talmud_Avodah_Zarah.53",
"children": [

{"title": "Halakhah 1",
"key": "Talmud/Yerushalmi/Seder Nezikin/Jerusalem Talmud Avodah Zarah/Daf 53/Halakhah 1",
"id": "Talmud.Yerushalmi.Seder_Nezikin.Jerusalem_Talmud_Avodah_Zarah.53.1",
"children": []}]},

{"title": "Daf 54",
"key": "Talmud/Yerushalmi/Seder Nezikin/Jerusalem Talmud Avodah Zarah/Daf 54",
"id": "Talmud.Yerushalmi.Seder_Nezikin.Jerusalem_Talmud_Avodah_Zarah.54",
"children": [

{"title": "Halakhah 1",
"key": "Talmud/Yerushalmi/Seder Nezikin/Jerusalem Talmud Avodah Zarah/Daf 54/Halakhah 1",
"id": "Talmud.Yerushalmi.Seder_Nezikin.Jerusalem_Talmud_Avodah_Zarah.54.1",
"children": []},

{"title": "Halakhah 2",
"key": "Talmud/Yerushalmi/Seder Nezikin/Jerusalem Talmud Avodah Zarah/Daf 54/Halakhah 2",
"id": "Talmud.Yerushalmi.Seder_Nezikin.Jerusalem_Talmud_Avodah_Zarah.54.2",
"children": []},

{"title": "Halakhah 3",
"key": "Talmud/Yerushalmi/Seder Nezikin/Jerusalem Talmud Avodah Zarah/Daf 54/Halakhah 3",
"id": "Talmud.Yerushalmi.Seder_Nezikin.Jerusalem_Talmud_Avodah_Zarah.54.3",
"children": []}]},

{"title": "Daf 55",
"key": "Talmud/Yerushalmi/Seder Nezikin/Jerusalem Talmud Avodah Zarah/Daf 55",
"id": "Talmud.Yerushalmi.Seder_Nezikin.Jerusalem_Talmud_Avodah_Zarah.55",
"children": [

{"title": "Halakhah 1",
"key": "Talmud/Yerushalmi/Seder Nezikin/Jerusalem Talmud Avodah Zarah/Daf 55/Halakhah 1",
"id": "Talmud.Yerushalmi.Seder_Nezikin.Jerusalem_Talmud_Avodah_Zarah.55.1",
"children": []},

{"title": "Halakhah 2",
"key": "Talmud/Yerushalmi/Seder Nezikin/Jerusalem Talmud Avodah Zarah/Daf 55/Halakhah 2",
"id": "Talmud.Yerushalmi.Seder_Nezikin.Jerusalem_Talmud_Avodah_Zarah.55.2",
"children": []},

{"title": "Halakhah 3",
"key": "Talmud/Yerushalmi/Seder Nezikin/Jerusalem Talmud Avodah Zarah/Daf 55/Halakhah 3",
"id": "Talmud.Yerushalmi.Seder_Nezikin.Jerusalem_Talmud_Avodah_Zarah.55.3",
"children": []},

{"title": "Halakhah 4",
"key": "Talmud/Yerushalmi/Seder Nezikin/Jerusalem Talmud Avodah Zarah/Daf 55/Halakhah 4",
"id": "Talmud.Yerushalmi.Seder_Nezikin.Jerusalem_Talmud_Avodah_Zarah.55.4",
"children": []},

{"title": "Halakhah 5",
"key": "Talmud/Yerushalmi/Seder Nezikin/Jerusalem Talmud Avodah Zarah/Daf 55/Halakhah 5",
"id": "Talmud.Yerushalmi.Seder_Nezikin.Jerusalem_Talmud_Avodah_Zarah.55.5",
"children": []}]},

{"title": "Daf 56",
"key": "Talmud/Yerushalmi/Seder Nezikin/Jerusalem Talmud Avodah Zarah/Daf 56",
"id": "Talmud.Yerushalmi.Seder_Nezikin.Jerusalem_Talmud_Avodah_Zarah.56",
"children": [

{"title": "Halakhah 1",
"key": "Talmud/Yerushalmi/Seder Nezikin/Jerusalem Talmud Avodah Zarah/Daf 56/Halakhah 1",
"id": "Talmud.Yerushalmi.Seder_Nezikin.Jerusalem_Talmud_Avodah_Zarah.56.1",
"children": []},

{"title": "Halakhah 2",
"key": "Talmud/Yerushalmi/Seder Nezikin/Jerusalem Talmud Avodah Zarah/Daf 56/Halakhah 2",
"id": "Talmud.Yerushalmi.Seder_Nezikin.Jerusalem_Talmud_Avodah_Zarah.56.2",
"children": []},

{"title": "Halakhah 3",
"key": "Talmud/Yerushalmi/Seder Nezikin/Jerusalem Talmud Avodah Zarah/Daf 56/Halakhah 3",
"id": "Talmud.Yerushalmi.Seder_Nezikin.Jerusalem_Talmud_Avodah_Zarah.56.3",
"children": []}]},

{"title": "Daf 57",
"key": "Talmud/Yerushalmi/Seder Nezikin/Jerusalem Talmud Avodah Zarah/Daf 57",
"id": "Talmud.Yerushalmi.Seder_Nezikin.Jerusalem_Talmud_Avodah_Zarah.57",
"children": [

{"title": "Halakhah 1",
"key": "Talmud/Yerushalmi/Seder Nezikin/Jerusalem Talmud Avodah Zarah/Daf 57/Halakhah 1",
"id": "Talmud.Yerushalmi.Seder_Nezikin.Jerusalem_Talmud_Avodah_Zarah.57.1",
"children": []},

{"title": "Halakhah 2",
"key": "Talmud/Yerushalmi/Seder Nezikin/Jerusalem Talmud Avodah Zarah/Daf 57/Halakhah 2",
"id": "Talmud.Yerushalmi.Seder_Nezikin.Jerusalem_Talmud_Avodah_Zarah.57.2",
"children": []}]},

{"title": "Daf 58",
"key": "Talmud/Yerushalmi/Seder Nezikin/Jerusalem Talmud Avodah Zarah/Daf 58",
"id": "Talmud.Yerushalmi.Seder_Nezikin.Jerusalem_Talmud_Avodah_Zarah.58",
"children": [

{"title": "Halakhah 1",
"key": "Talmud/Yerushalmi/Seder Nezikin/Jerusalem Talmud Avodah Zarah/Daf 58/Halakhah 1",
"id": "Talmud.Yerushalmi.Seder_Nezikin.Jerusalem_Talmud_Avodah_Zarah.58.1",
"children": []},

{"title": "Halakhah 2",
"key": "Talmud/Yerushalmi/Seder Nezikin/Jerusalem Talmud Avodah Zarah/Daf 58/Halakhah 2",
"id": "Talmud.Yerushalmi.Seder_Nezikin.Jerusalem_Talmud_Avodah_Zarah.58.2",
"children": []}]},

{"title": "Daf 59",
"key": "Talmud/Yerushalmi/Seder Nezikin/Jerusalem Talmud Avodah Zarah/Daf 59",
"id": "Talmud.Yerushalmi.Seder_Nezikin.Jerusalem_Talmud_Avodah_Zarah.59",
"children": [

{"title": "Halakhah 1",
"key": "Talmud/Yerushalmi/Seder Nezikin/Jerusalem Talmud Avodah Zarah/Daf 59/Halakhah 1",
"id": "Talmud.Yerushalmi.Seder_Nezikin.Jerusalem_Talmud_Avodah_Zarah.59.1",
"children": []},

{"title": "Halakhah 2",
"key": "Talmud/Yerushalmi/Seder Nezikin/Jerusalem Talmud Avodah Zarah/Daf 59/Halakhah 2",
"id": "Talmud.Yerushalmi.Seder_Nezikin.Jerusalem_Talmud_Avodah_Zarah.59.2",
"children": []},

{"title": "Halakhah 3",
"key": "Talmud/Yerushalmi/Seder Nezikin/Jerusalem Talmud Avodah Zarah/Daf 59/Halakhah 3",
"id": "Talmud.Yerushalmi.Seder_Nezikin.Jerusalem_Talmud_Avodah_Zarah.59.3",
"children": []},

{"title": "Halakhah 4",
"key": "Talmud/Yerushalmi/Seder Nezikin/Jerusalem Talmud Avodah Zarah/Daf 59/Halakhah 4",
"id": "Talmud.Yerushalmi.Seder_Nezikin.Jerusalem_Talmud_Avodah_Zarah.59.4",
"children": []}]},

{"title": "Daf 60",
"key": "Talmud/Yerushalmi/Seder Nezikin/Jerusalem Talmud Avodah Zarah/Daf 60",
"id": "Talmud.Yerushalmi.Seder_Nezikin.Jerusalem_Talmud_Avodah_Zarah.60",
"children": [

{"title": "Halakhah 1",
"key": "Talmud/Yerushalmi/Seder Nezikin/Jerusalem Talmud Avodah Zarah/Daf 60/Halakhah 1",
"id": "Talmud.Yerushalmi.Seder_Nezikin.Jerusalem_Talmud_Avodah_Zarah.60.1",
"children": []},

{"title": "Halakhah 2",
"key": "Talmud/Yerushalmi/Seder Nezikin/Jerusalem Talmud Avodah Zarah/Daf 60/Halakhah 2",
"id": "Talmud.Yerushalmi.Seder_Nezikin.Jerusalem_Talmud_Avodah_Zarah.60.2",
"children": []}]},

{"title": "Daf 61",
"key": "Talmud/Yerushalmi/Seder Nezikin/Jerusalem Talmud Avodah Zarah/Daf 61",
"id": "Talmud.Yerushalmi.Seder_Nezikin.Jerusalem_Talmud_Avodah_Zarah.61",
"children": [

{"title": "Halakhah 1",
"key": "Talmud/Yerushalmi/Seder Nezikin/Jerusalem Talmud Avodah Zarah/Daf 61/Halakhah 1",
"id": "Talmud.Yerushalmi.Seder_Nezikin.Jerusalem_Talmud_Avodah_Zarah.61.1",
"children": []},

{"title": "Halakhah 2",
"key": "Talmud/Yerushalmi/Seder Nezikin/Jerusalem Talmud Avodah Zarah/Daf 61/Halakhah 2",
"id": "Talmud.Yerushalmi.Seder_Nezikin.Jerusalem_Talmud_Avodah_Zarah.61.2",
"children": []},

{"title": "Halakhah 3",
"key": "Talmud/Yerushalmi/Seder Nezikin/Jerusalem Talmud Avodah Zarah/Daf 61/Halakhah 3",
"id": "Talmud.Yerushalmi.Seder_Nezikin.Jerusalem_Talmud_Avodah_Zarah.61.3",
"children": []},

{"title": "Halakhah 4",
"key": "Talmud/Yerushalmi/Seder Nezikin/Jerusalem Talmud Avodah Zarah/Daf 61/Halakhah 4",
"id": "Talmud.Yerushalmi.Seder_Nezikin.Jerusalem_Talmud_Avodah_Zarah.61.4",
"children": []}]},

{"title": "Daf 62",
"key": "Talmud/Yerushalmi/Seder Nezikin/Jerusalem Talmud Avodah Zarah/Daf 62",
"id": "Talmud.Yerushalmi.Seder_Nezikin.Jerusalem_Talmud_Avodah_Zarah.62",
"children": [

{"title": "Halakhah 1",
"key": "Talmud/Yerushalmi/Seder Nezikin/Jerusalem Talmud Avodah Zarah/Daf 62/Halakhah 1",
"id": "Talmud.Yerushalmi.Seder_Nezikin.Jerusalem_Talmud_Avodah_Zarah.62.1",
"children": []}]},

{"title": "Daf 63",
"key": "Talmud/Yerushalmi/Seder Nezikin/Jerusalem Talmud Avodah Zarah/Daf 63",
"id": "Talmud.Yerushalmi.Seder_Nezikin.Jerusalem_Talmud_Avodah_Zarah.63",
"children": [

{"title": "Halakhah 1",
"key": "Talmud/Yerushalmi/Seder Nezikin/Jerusalem Talmud Avodah Zarah/Daf 63/Halakhah 1",
"id": "Talmud.Yerushalmi.Seder_Nezikin.Jerusalem_Talmud_Avodah_Zarah.63.1",
"children": []},

{"title": "Halakhah 2",
"key": "Talmud/Yerushalmi/Seder Nezikin/Jerusalem Talmud Avodah Zarah/Daf 63/Halakhah 2",
"id": "Talmud.Yerushalmi.Seder_Nezikin.Jerusalem_Talmud_Avodah_Zarah.63.2",
"children": []},

{"title": "Halakhah 3",
"key": "Talmud/Yerushalmi/Seder Nezikin/Jerusalem Talmud Avodah Zarah/Daf 63/Halakhah 3",
"id": "Talmud.Yerushalmi.Seder_Nezikin.Jerusalem_Talmud_Avodah_Zarah.63.3",
"children": []}]},

{"title": "Daf 64",
"key": "Talmud/Yerushalmi/Seder Nezikin/Jerusalem Talmud Avodah Zarah/Daf 64",
"id": "Talmud.Yerushalmi.Seder_Nezikin.Jerusalem_Talmud_Avodah_Zarah.64",
"children": [

{"title": "Halakhah 1",
"key": "Talmud/Yerushalmi/Seder Nezikin/Jerusalem Talmud Avodah Zarah/Daf 64/Halakhah 1",
"id": "Talmud.Yerushalmi.Seder_Nezikin.Jerusalem_Talmud_Avodah_Zarah.64.1",
"children": []},

{"title": "Halakhah 2",
"key": "Talmud/Yerushalmi/Seder Nezikin/Jerusalem Talmud Avodah Zarah/Daf 64/Halakhah 2",
"id": "Talmud.Yerushalmi.Seder_Nezikin.Jerusalem_Talmud_Avodah_Zarah.64.2",
"children": []}]},

{"title": "Daf 65",
"key": "Talmud/Yerushalmi/Seder Nezikin/Jerusalem Talmud Avodah Zarah/Daf 65",
"id": "Talmud.Yerushalmi.Seder_Nezikin.Jerusalem_Talmud_Avodah_Zarah.65",
"children": [

{"title": "Halakhah 1",
"key": "Talmud/Yerushalmi/Seder Nezikin/Jerusalem Talmud Avodah Zarah/Daf 65/Halakhah 1",
"id": "Talmud.Yerushalmi.Seder_Nezikin.Jerusalem_Talmud_Avodah_Zarah.65.1",
"children": []},

{"title": "Halakhah 2",
"key": "Talmud/Yerushalmi/Seder Nezikin/Jerusalem Talmud Avodah Zarah/Daf 65/Halakhah 2",
"id": "Talmud.Yerushalmi.Seder_Nezikin.Jerusalem_Talmud_Avodah_Zarah.65.2",
"children": []},

{"title": "Halakhah 3",
"key": "Talmud/Yerushalmi/Seder Nezikin/Jerusalem Talmud Avodah Zarah/Daf 65/Halakhah 3",
"id": "Talmud.Yerushalmi.Seder_Nezikin.Jerusalem_Talmud_Avodah_Zarah.65.3",
"children": []}]},

{"title": "Daf 66",
"key": "Talmud/Yerushalmi/Seder Nezikin/Jerusalem Talmud Avodah Zarah/Daf 66",
"id": "Talmud.Yerushalmi.Seder_Nezikin.Jerusalem_Talmud_Avodah_Zarah.66",
"children": [

{"title": "Halakhah 1",
"key": "Talmud/Yerushalmi/Seder Nezikin/Jerusalem Talmud Avodah Zarah/Daf 66/Halakhah 1",
"id": "Talmud.Yerushalmi.Seder_Nezikin.Jerusalem_Talmud_Avodah_Zarah.66.1",
"children": []}]},

{"title": "Daf 67",
"key": "Talmud/Yerushalmi/Seder Nezikin/Jerusalem Talmud Avodah Zarah/Daf 67",
"id": "Talmud.Yerushalmi.Seder_Nezikin.Jerusalem_Talmud_Avodah_Zarah.67",
"children": [

{"title": "Halakhah 1",
"key": "Talmud/Yerushalmi/Seder Nezikin/Jerusalem Talmud Avodah Zarah/Daf 67/Halakhah 1",
"id": "Talmud.Yerushalmi.Seder_Nezikin.Jerusalem_Talmud_Avodah_Zarah.67.1",
"children": []},

{"title": "Halakhah 2",
"key": "Talmud/Yerushalmi/Seder Nezikin/Jerusalem Talmud Avodah Zarah/Daf 67/Halakhah 2",
"id": "Talmud.Yerushalmi.Seder_Nezikin.Jerusalem_Talmud_Avodah_Zarah.67.2",
"children": []},

{"title": "Halakhah 3",
"key": "Talmud/Yerushalmi/Seder Nezikin/Jerusalem Talmud Avodah Zarah/Daf 67/Halakhah 3",
"id": "Talmud.Yerushalmi.Seder_Nezikin.Jerusalem_Talmud_Avodah_Zarah.67.3",
"children": []},

{"title": "Halakhah 4",
"key": "Talmud/Yerushalmi/Seder Nezikin/Jerusalem Talmud Avodah Zarah/Daf 67/Halakhah 4",
"id": "Talmud.Yerushalmi.Seder_Nezikin.Jerusalem_Talmud_Avodah_Zarah.67.4",
"children": []},

{"title": "Halakhah 5",
"key": "Talmud/Yerushalmi/Seder Nezikin/Jerusalem Talmud Avodah Zarah/Daf 67/Halakhah 5",
"id": "Talmud.Yerushalmi.Seder_Nezikin.Jerusalem_Talmud_Avodah_Zarah.67.5",
"children": []},

{"title": "Halakhah 6",
"key": "Talmud/Yerushalmi/Seder Nezikin/Jerusalem Talmud Avodah Zarah/Daf 67/Halakhah 6",
"id": "Talmud.Yerushalmi.Seder_Nezikin.Jerusalem_Talmud_Avodah_Zarah.67.6",
"children": []}]},

{"title": "Daf 68",
"key": "Talmud/Yerushalmi/Seder Nezikin/Jerusalem Talmud Avodah Zarah/Daf 68",
"id": "Talmud.Yerushalmi.Seder_Nezikin.Jerusalem_Talmud_Avodah_Zarah.68",
"children": [

{"title": "Halakhah 1",
"key": "Talmud/Yerushalmi/Seder Nezikin/Jerusalem Talmud Avodah Zarah/Daf 68/Halakhah 1",
"id": "Talmud.Yerushalmi.Seder_Nezikin.Jerusalem_Talmud_Avodah_Zarah.68.1",
"children": []},

{"title": "Halakhah 2",
"key": "Talmud/Yerushalmi/Seder Nezikin/Jerusalem Talmud Avodah Zarah/Daf 68/Halakhah 2",
"id": "Talmud.Yerushalmi.Seder_Nezikin.Jerusalem_Talmud_Avodah_Zarah.68.2",
"children": []},

{"title": "Halakhah 3",
"key": "Talmud/Yerushalmi/Seder Nezikin/Jerusalem Talmud Avodah Zarah/Daf 68/Halakhah 3",
"id": "Talmud.Yerushalmi.Seder_Nezikin.Jerusalem_Talmud_Avodah_Zarah.68.3",
"children": []},

{"title": "Halakhah 4",
"key": "Talmud/Yerushalmi/Seder Nezikin/Jerusalem Talmud Avodah Zarah/Daf 68/Halakhah 4",
"id": "Talmud.Yerushalmi.Seder_Nezikin.Jerusalem_Talmud_Avodah_Zarah.68.4",
"children": []}]},

{"title": "Daf 69",
"key": "Talmud/Yerushalmi/Seder Nezikin/Jerusalem Talmud Avodah Zarah/Daf 69",
"id": "Talmud.Yerushalmi.Seder_Nezikin.Jerusalem_Talmud_Avodah_Zarah.69",
"children": [

{"title": "Halakhah 1",
"key": "Talmud/Yerushalmi/Seder Nezikin/Jerusalem Talmud Avodah Zarah/Daf 69/Halakhah 1",
"id": "Talmud.Yerushalmi.Seder_Nezikin.Jerusalem_Talmud_Avodah_Zarah.69.1",
"children": []},

{"title": "Halakhah 2",
"key": "Talmud/Yerushalmi/Seder Nezikin/Jerusalem Talmud Avodah Zarah/Daf 69/Halakhah 2",
"id": "Talmud.Yerushalmi.Seder_Nezikin.Jerusalem_Talmud_Avodah_Zarah.69.2",
"children": []},

{"title": "Halakhah 3",
"key": "Talmud/Yerushalmi/Seder Nezikin/Jerusalem Talmud Avodah Zarah/Daf 69/Halakhah 3",
"id": "Talmud.Yerushalmi.Seder_Nezikin.Jerusalem_Talmud_Avodah_Zarah.69.3",
"children": []},

{"title": "Halakhah 4",
"key": "Talmud/Yerushalmi/Seder Nezikin/Jerusalem Talmud Avodah Zarah/Daf 69/Halakhah 4",
"id": "Talmud.Yerushalmi.Seder_Nezikin.Jerusalem_Talmud_Avodah_Zarah.69.4",
"children": []},

{"title": "Halakhah 5",
"key": "Talmud/Yerushalmi/Seder Nezikin/Jerusalem Talmud Avodah Zarah/Daf 69/Halakhah 5",
"id": "Talmud.Yerushalmi.Seder_Nezikin.Jerusalem_Talmud_Avodah_Zarah.69.5",
"children": []}]},

{"title": "Daf 70",
"key": "Talmud/Yerushalmi/Seder Nezikin/Jerusalem Talmud Avodah Zarah/Daf 70",
"id": "Talmud.Yerushalmi.Seder_Nezikin.Jerusalem_Talmud_Avodah_Zarah.70",
"children": [

{"title": "Halakhah 1",
"key": "Talmud/Yerushalmi/Seder Nezikin/Jerusalem Talmud Avodah Zarah/Daf 70/Halakhah 1",
"id": "Talmud.Yerushalmi.Seder_Nezikin.Jerusalem_Talmud_Avodah_Zarah.70.1",
"children": []},

{"title": "Halakhah 2",
"key": "Talmud/Yerushalmi/Seder Nezikin/Jerusalem Talmud Avodah Zarah/Daf 70/Halakhah 2",
"id": "Talmud.Yerushalmi.Seder_Nezikin.Jerusalem_Talmud_Avodah_Zarah.70.2",
"children": []},

{"title": "Halakhah 3",
"key": "Talmud/Yerushalmi/Seder Nezikin/Jerusalem Talmud Avodah Zarah/Daf 70/Halakhah 3",
"id": "Talmud.Yerushalmi.Seder_Nezikin.Jerusalem_Talmud_Avodah_Zarah.70.3",
"children": []}]},

{"title": "Daf 71",
"key": "Talmud/Yerushalmi/Seder Nezikin/Jerusalem Talmud Avodah Zarah/Daf 71",
"id": "Talmud.Yerushalmi.Seder_Nezikin.Jerusalem_Talmud_Avodah_Zarah.71",
"children": [

{"title": "Halakhah 1",
"key": "Talmud/Yerushalmi/Seder Nezikin/Jerusalem Talmud Avodah Zarah/Daf 71/Halakhah 1",
"id": "Talmud.Yerushalmi.Seder_Nezikin.Jerusalem_Talmud_Avodah_Zarah.71.1",
"children": []},

{"title": "Halakhah 2",
"key": "Talmud/Yerushalmi/Seder Nezikin/Jerusalem Talmud Avodah Zarah/Daf 71/Halakhah 2",
"id": "Talmud.Yerushalmi.Seder_Nezikin.Jerusalem_Talmud_Avodah_Zarah.71.2",
"children": []}]},

{"title": "Daf 72",
"key": "Talmud/Yerushalmi/Seder Nezikin/Jerusalem Talmud Avodah Zarah/Daf 72",
"id": "Talmud.Yerushalmi.Seder_Nezikin.Jerusalem_Talmud_Avodah_Zarah.72",
"children": [

{"title": "Halakhah 1",
"key": "Talmud/Yerushalmi/Seder Nezikin/Jerusalem Talmud Avodah Zarah/Daf 72/Halakhah 1",
"id": "Talmud.Yerushalmi.Seder_Nezikin.Jerusalem_Talmud_Avodah_Zarah.72.1",
"children": []},

{"title": "Halakhah 2",
"key": "Talmud/Yerushalmi/Seder Nezikin/Jerusalem Talmud Avodah Zarah/Daf 72/Halakhah 2",
"id": "Talmud.Yerushalmi.Seder_Nezikin.Jerusalem_Talmud_Avodah_Zarah.72.2",
"children": []},

{"title": "Halakhah 3",
"key": "Talmud/Yerushalmi/Seder Nezikin/Jerusalem Talmud Avodah Zarah/Daf 72/Halakhah 3",
"id": "Talmud.Yerushalmi.Seder_Nezikin.Jerusalem_Talmud_Avodah_Zarah.72.3",
"children": []},

{"title": "Halakhah 4",
"key": "Talmud/Yerushalmi/Seder Nezikin/Jerusalem Talmud Avodah Zarah/Daf 72/Halakhah 4",
"id": "Talmud.Yerushalmi.Seder_Nezikin.Jerusalem_Talmud_Avodah_Zarah.72.4",
"children": []}]},

{"title": "Daf 73",
"key": "Talmud/Yerushalmi/Seder Nezikin/Jerusalem Talmud Avodah Zarah/Daf 73",
"id": "Talmud.Yerushalmi.Seder_Nezikin.Jerusalem_Talmud_Avodah_Zarah.73",
"children": [

{"title": "Halakhah 1",
"key": "Talmud/Yerushalmi/Seder Nezikin/Jerusalem Talmud Avodah Zarah/Daf 73/Halakhah 1",
"id": "Talmud.Yerushalmi.Seder_Nezikin.Jerusalem_Talmud_Avodah_Zarah.73.1",
"children": []},

{"title": "Halakhah 2",
"key": "Talmud/Yerushalmi/Seder Nezikin/Jerusalem Talmud Avodah Zarah/Daf 73/Halakhah 2",
"id": "Talmud.Yerushalmi.Seder_Nezikin.Jerusalem_Talmud_Avodah_Zarah.73.2",
"children": []},

{"title": "Halakhah 3",
"key": "Talmud/Yerushalmi/Seder Nezikin/Jerusalem Talmud Avodah Zarah/Daf 73/Halakhah 3",
"id": "Talmud.Yerushalmi.Seder_Nezikin.Jerusalem_Talmud_Avodah_Zarah.73.3",
"children": []},

{"title": "Halakhah 4",
"key": "Talmud/Yerushalmi/Seder Nezikin/Jerusalem Talmud Avodah Zarah/Daf 73/Halakhah 4",
"id": "Talmud.Yerushalmi.Seder_Nezikin.Jerusalem_Talmud_Avodah_Zarah.73.4",
"children": []}]},

{"title": "Daf 74",
"key": "Talmud/Yerushalmi/Seder Nezikin/Jerusalem Talmud Avodah Zarah/Daf 74",
"id": "Talmud.Yerushalmi.Seder_Nezikin.Jerusalem_Talmud_Avodah_Zarah.74",
"children": [

{"title": "Halakhah 1",
"key": "Talmud/Yerushalmi/Seder Nezikin/Jerusalem Talmud Avodah Zarah/Daf 74/Halakhah 1",
"id": "Talmud.Yerushalmi.Seder_Nezikin.Jerusalem_Talmud_Avodah_Zarah.74.1",
"children": []},

{"title": "Halakhah 2",
"key": "Talmud/Yerushalmi/Seder Nezikin/Jerusalem Talmud Avodah Zarah/Daf 74/Halakhah 2",
"id": "Talmud.Yerushalmi.Seder_Nezikin.Jerusalem_Talmud_Avodah_Zarah.74.2",
"children": []}]}]